MANIFEST.in
NEWS.txt
README.md
setup.py
src/WebTestRunner.egg-info/PKG-INFO
src/WebTestRunner.egg-info/SOURCES.txt
src/WebTestRunner.egg-info/dependency_links.txt
src/WebTestRunner.egg-info/entry_points.txt
src/WebTestRunner.egg-info/not-zip-safe
src/WebTestRunner.egg-info/requires.txt
src/WebTestRunner.egg-info/top_level.txt
src/webtestrunner/__init__.py
src/webtestrunner/loader.py
src/webtestrunner/runner.py
src/webtestrunner/server.py
src/webtestrunner/static/css/bootstrap.min.css
src/webtestrunner/static/css/rainbow.css
src/webtestrunner/static/css/styles.css
src/webtestrunner/static/img/glyphicons-halflings-white.png
src/webtestrunner/static/img/glyphicons-halflings.png
src/webtestrunner/static/js/app.js
src/webtestrunner/static/js/modules/library.js
src/webtestrunner/static/js/modules/namespace.js
src/webtestrunner/static/js/modules/router.js
src/webtestrunner/static/js/modules/status.js
src/webtestrunner/static/js/modules/tests.js
src/webtestrunner/static/js/vendor/backbone-0.9.2.min.js
src/webtestrunner/static/js/vendor/bootstrap-alert.js
src/webtestrunner/static/js/vendor/bootstrap-modal.min.js
src/webtestrunner/static/js/vendor/bootstrap.min.js
src/webtestrunner/static/js/vendor/jquery-1.7.2.min.js
src/webtestrunner/static/js/vendor/rainbow-custom.min.js
src/webtestrunner/static/js/vendor/underscore-1.3.1.min.js
src/webtestrunner/templates/index.html
src/webtestrunner/tests/__init__.py
src/webtestrunner/tests/tests.py