Metadata-Version: 1.0
Name: WebTestRunner
Version: 0.2
Summary: Web-based interface for selectively executing client-side Python UnitTests
Home-page: https://github.com/jessejlt
Author: Jesse Thompson
Author-email: jessejlt@gmail.com
License: MIT
Keywords: unittest
Platform: UNKNOWN
